dami_rand_algo.py
dami_rand_algo-0.1.1.dist-info/entry_points.txt
dami_rand_algo-0.1.1.dist-info/LICENSE.txt
dami_rand_algo-0.1.1.dist-info/WHEEL
dami_rand_algo-0.1.1.dist-info/METADATA
dami_rand_algo-0.1.1.dist-info/RECORD
